MANIFEST.in
README
setup.py
fugue_icons/__init__.py
fugue_icons/blueprint.py
fugue_icons/fugue_make.py
fugue_icons/models.py
fugue_icons.egg-info/PKG-INFO
fugue_icons.egg-info/SOURCES.txt
fugue_icons.egg-info/dependency_links.txt
fugue_icons.egg-info/not-zip-safe
fugue_icons.egg-info/requires.txt
fugue_icons.egg-info/top_level.txt
fugue_icons/static/fugue-icons-important.css
fugue_icons/static/fugue-icons.css
fugue_icons/static/fugue-icons.json
fugue_icons/static/fugue-icons.png