Metadata-Version: 1.1
Name: fugue-icons
Version: 3.5.6
Summary: Fugue Icons packaged for simple use in web apps.
Home-page: https://bitbucket.org/thesheep/fugue-icons/
Author: Radomir Dopieralski
Author-email: fugue@sheep.art.pl
License: MIT
Download-URL: https://bitbucket.org/thesheep/fugue-icons/get/master.tar.gz
Keywords: icon css sprite graphics ui
Platform: any
Classifier: Development Status :: 6 - Mature
Classifier: Environment :: Web Environment
Classifier: Intended Audience :: Developers
Classifier: License :: OSI Approved :: MIT License
Classifier: Operating System :: OS Independent
Classifier: Programming Language :: Python
Classifier: Topic :: Multimedia :: Graphics
Classifier: Topic :: Scientific/Engineering :: Human Machine Interfaces
Classifier: Topic :: Scientific/Engineering :: Visualization
Classifier: Topic :: Software Development :: Libraries :: Python Modules
Classifier: Topic :: Software Development :: User Interfaces
